psycop_feature_generation/__init__.py
psycop_feature_generation/utils.py
psycop_feature_generation/utils_for_testing.py
psycop_feature_generation/application_modules/__init__.py
psycop_feature_generation/application_modules/describe_flattened_dataset.py
psycop_feature_generation/application_modules/filter_prediction_times.py
psycop_feature_generation/application_modules/flatten_dataset.py
psycop_feature_generation/application_modules/loggers.py
psycop_feature_generation/application_modules/project_setup.py
psycop_feature_generation/application_modules/save_dataset_to_disk.py
psycop_feature_generation/application_modules/utils.py
psycop_feature_generation/application_modules/wandb_utils.py
psycop_feature_generation/data_checks/__init__.py
psycop_feature_generation/data_checks/utils.py
psycop_feature_generation/data_checks/flattened/data_integrity.py
psycop_feature_generation/data_checks/flattened/feature_describer.py
psycop_feature_generation/data_checks/raw/check_predictor_lists.py
psycop_feature_generation/data_checks/raw/check_raw_df.py
psycop_feature_generation/data_checks/raw/validate_raw_data.py
psycop_feature_generation/loaders/__init__.py
psycop_feature_generation/loaders/non_numerical_coercer.py
psycop_feature_generation/loaders/example/__init__.py
psycop_feature_generation/loaders/example/debug_loader_function.py
psycop_feature_generation/loaders/example/load_bmi.py
psycop_feature_generation/loaders/example/load_coercion.py
psycop_feature_generation/loaders/example/load_diagnoses.py
psycop_feature_generation/loaders/example/load_lab_results.py
psycop_feature_generation/loaders/example/load_medications.py
psycop_feature_generation/loaders/example/load_physical_visits.py
psycop_feature_generation/loaders/example/load_sql.py
psycop_feature_generation/loaders/example/load_structured_sfi.py
psycop_feature_generation/loaders/example/load_text.py
psycop_feature_generation/loaders/filters/__init__.py
psycop_feature_generation/loaders/filters/diabetes_filters.py
psycop_feature_generation-0.23.0.dist-info/METADATA
psycop_feature_generation-0.23.0.dist-info/WHEEL
psycop_feature_generation-0.23.0.dist-info/top_level.txt
psycop_feature_generation-0.23.0.dist-info/RECORD
