Metadata-Version: 2.1
Name: psycop-feature-generation
Version: 0.23.0
Author-email: Martin Bernstorff <martinbernstorfff@gmail.com>
Classifier: Operating System :: POSIX :: Linux
Classifier: Operating System :: MacOS :: MacOS X
Classifier: Operating System :: Microsoft :: Windows
Classifier: Programming Language :: Python :: 3
Classifier: Programming Language :: Python :: 3.8
Classifier: Programming Language :: Python :: 3.9
Classifier: Programming Language :: Python :: 3.10
Requires-Python: >=3.9
Requires-Dist: wasabi (<1.1.2,>=0.9.1)
Requires-Dist: scikit-learn (<1.2.3,>=1.1.2)
Requires-Dist: wandb (<0.15.1,>=0.12.0)
Requires-Dist: deepchecks (<0.12.0,>=0.8.0)
Requires-Dist: dill (<0.3.7,>=0.3.0)
Requires-Dist: srsly (<2.4.6,>=2.4.4)
Requires-Dist: SQLAlchemy (<2.0.11,>=1.4.41)
Requires-Dist: pyodbc (<4.0.40,>=4.0.34)
Requires-Dist: dask (<2023.5.0,>=2022.9.0)
Requires-Dist: pydantic (<1.11.0,>=1.9.0)
Requires-Dist: psutil (<6.0.0,>=5.9.1)
Requires-Dist: pandas (<2.1.0,>=1.4.0)
Requires-Dist: catalogue (<2.1.0,>=2.0.0)
Requires-Dist: numpy (<1.24.4,>=1.23.3)
Requires-Dist: transformers (<5.0.0,>=4.22.2)
Requires-Dist: pyarrow (<11.1.0,>=9.0.0)
Requires-Dist: psycopmlutils (<0.12.0,>=0.2.4)
Requires-Dist: protobuf (<=3.20.3)
Requires-Dist: frozendict (>=2.3.4)
Provides-Extra: dev
Requires-Dist: cruft ; extra == 'dev'
Requires-Dist: pylint ; extra == 'dev'
Requires-Dist: ruff ; extra == 'dev'
Requires-Dist: black (<23.1.1,>=22.8.0) ; extra == 'dev'
Requires-Dist: docformatter (<1.6.4,>=1.5.0) ; extra == 'dev'
Requires-Dist: pre-commit (==3.2.2) ; extra == 'dev'
Requires-Dist: mypy (==1.2.0) ; extra == 'dev'
Requires-Dist: pydantic ; extra == 'dev'
Provides-Extra: tests
Requires-Dist: pytest (<7.3.2,>=7.1.3) ; extra == 'tests'
Requires-Dist: pytest-cov (<4.0.1,>=3.0.0) ; extra == 'tests'
Requires-Dist: pytest-xdist (<3.2.1,>=2.4.0) ; extra == 'tests'
Requires-Dist: timeseriesflattener (>=0.21.0) ; extra == 'tests'
